apologies/__init__.py
apologies/cli.py
apologies/demo.py
apologies/demo_unix.py
apologies/demo_windows.py
apologies/engine.py
apologies/game.py
apologies/py.typed
apologies/render.py
apologies/reward.py
apologies/rules.py
apologies/simulation.py
apologies/source.py
apologies/util.py
apologies-0.4.2.dist-info/METADATA
apologies-0.4.2.dist-info/WHEEL
apologies-0.4.2.dist-info/licenses/LICENSE
apologies-0.4.2.dist-info/licenses/NOTICE
apologies-0.4.2.dist-info/RECORD
