Metadata-Version: 2.4
Name: apologies
Version: 0.4.2
Summary: Python code to play a game similar to Sorry
Project-URL: Homepage, https://pypi.org/project/apologies/
Project-URL: Repository, https://github.com/pronovic/apologies
Project-URL: Changelog, https://github.com/pronovic/apologies/releases
Project-URL: Documentation, https://apologies.readthedocs.io/en/stable/
Project-URL: Issues, https://github.com/pronovic/apologies/issues
Author-email: "Kenneth J. Pronovici" <pronovic@ieee.org>
License-Expression: Apache-2.0
License-File: LICENSE
License-File: NOTICE
Classifier: Environment :: Console
Classifier: Intended Audience :: Developers
Classifier: Natural Language :: English
Classifier: Operating System :: OS Independent
Classifier: Programming Language :: Python :: 3
Classifier: Programming Language :: Python :: 3.11
Classifier: Programming Language :: Python :: 3.12
Classifier: Programming Language :: Python :: 3.13
Classifier: Programming Language :: Python :: 3.14
Classifier: Topic :: Games/Entertainment :: Board Games
Classifier: Topic :: Software Development :: Libraries
Requires-Python: <4,>=3.11
Requires-Dist: arrow<2.0.0,>=1.3.0
Requires-Dist: attrs>=24.2.0
Requires-Dist: cattrs>=24.1.2
Provides-Extra: docs
Requires-Dist: sphinx-autoapi<4.0.0,>=3.3.3; extra == 'docs'
Requires-Dist: sphinx<9.0.0,>=8.1.3; extra == 'docs'
